pytankerkoenig/__init__.py
pytankerkoenig-0.0.1.dist-info/METADATA
pytankerkoenig-0.0.1.dist-info/RECORD
pytankerkoenig-0.0.1.dist-info/WHEEL
pytankerkoenig-0.0.1.dist-info/top_level.txt
