Metadata-Version: 2.1
Name: pytankerkoenig
Version: 0.0.1
Summary: Library for Tankerönig.de JSON API
Home-page: https://github.com/ultrara1n/tankerkoenig-api
Author: Philipp Wensauer
Author-email: mail@philippwensauer.com
License: UNKNOWN
Platform: UNKNOWN
Classifier: Programming Language :: Python :: 3
Classifier: License :: OSI Approved :: MIT License
Classifier: Operating System :: OS Independent
Classifier: Intended Audience :: Developers
